awModelUpload/__init__.py
awModelUpload/awModelUpload.py
awModelUpload-0.0.3.dist-info/LICENCE
awModelUpload-0.0.3.dist-info/METADATA
awModelUpload-0.0.3.dist-info/WHEEL
awModelUpload-0.0.3.dist-info/top_level.txt
awModelUpload-0.0.3.dist-info/RECORD
