Metadata-Version: 2.1
Name: awModelUpload
Version: 0.0.3
Summary: I-WUNDER DSW
Author-email: OOK <omerkutsal@gmail.com>
Classifier: Programming Language :: Python :: 3
Classifier: License :: OSI Approved :: MIT License
Classifier: Operating System :: OS Independent
Requires-Python: >=3.7
License-File: LICENCE
Requires-Dist: selenium (==4.8.2)
